{
  "items": [
    {
      "name": "Landing",
      "price": "€399",
      "hint": "Perfect for one offer / one goal",
      "bullets": ["1 page", "Responsive design", "CTA + contact form", "Basic SEO", "Deploy to Vercel"],
      "cta": "Start Landing"
    },
    {
      "name": "Business",
      "price": "€799",
      "hint": "Most popular for small companies",
      "featured": true,
      "bullets": ["Up to 5 pages", "Services + Portfolio", "Copy improvements", "Speed optimization", "Analytics setup"],
      "cta": "Start Business"
    },
    {
      "name": "Custom",
      "price": "From €1200",
      "hint": "When you need something specific",
      "bullets": ["Custom pages", "Advanced sections", "Integrations", "Multilingual", "Priority support"],
      "cta": "Get a quote"
    }
  ]
}
