{
  "hero": {
    "title": "Fast Websites for Small Business",
    "subtitle": "Professional landing pages and business websites delivered in days, not months. Simple pricing, clear timelines, guaranteed results."
  },
  "problems": {
    "title": "The Problem with Most Web Agencies",
    "subtitle": "Traditional web development is slow, expensive, and unpredictable."
  },
  "solutions": {
    "title": "Our Solution: Fast, Fixed-Price Websites",
    "subtitle": "We deliver clean, modern websites in days — with fixed price, clear scope and deadline."
  },
  "process": {
    "title": "Simple 4-Step Process",
    "subtitle": "Brief → Design → Build → Launch. No chaos."
  }
}
